fuc/__init__.py
fuc/__main__.py
fuc/version.py
fuc/api/__init__.py
fuc/api/common.py
fuc/api/pybam.py
fuc/api/pybed.py
fuc/api/pychip.py
fuc/api/pycov.py
fuc/api/pyfq.py
fuc/api/pygff.py
fuc/api/pykallisto.py
fuc/api/pymaf.py
fuc/api/pysnpeff.py
fuc/api/pyvcf.py
fuc/api/pyvep.py
fuc/cli/__init__.py
fuc/cli/bam_aldepth.py
fuc/cli/bam_depth.py
fuc/cli/bam_head.py
fuc/cli/bam_index.py
fuc/cli/bam_rename.py
fuc/cli/bam_slice.py
fuc/cli/bed_intxn.py
fuc/cli/bed_sum.py
fuc/cli/cov_concat.py
fuc/cli/cov_rename.py
fuc/cli/fa_filter.py
fuc/cli/fq_count.py
fuc/cli/fq_sum.py
fuc/cli/fuc_bgzip.py
fuc/cli/fuc_compf.py
fuc/cli/fuc_demux.py
fuc/cli/fuc_exist.py
fuc/cli/fuc_find.py
fuc/cli/fuc_undetm.py
fuc/cli/maf_maf2vcf.py
fuc/cli/maf_oncoplt.py
fuc/cli/maf_sumplt.py
fuc/cli/maf_vcf2maf.py
fuc/cli/ngs_bam2fq.py
fuc/cli/ngs_fq2bam.py
fuc/cli/ngs_hc.py
fuc/cli/ngs_m2.py
fuc/cli/ngs_pon.py
fuc/cli/ngs_quant.py
fuc/cli/ngs_trim.py
fuc/cli/tabix_index.py
fuc/cli/tabix_slice.py
fuc/cli/tbl_merge.py
fuc/cli/tbl_sum.py
fuc/cli/vcf_call.py
fuc/cli/vcf_filter.py
fuc/cli/vcf_index.py
fuc/cli/vcf_merge.py
fuc/cli/vcf_rename.py
fuc/cli/vcf_slice.py
fuc/cli/vcf_split.py
fuc/cli/vcf_vcf2bed.py
fuc/cli/vcf_vep.py
fuc-0.38.0.dist-info/LICENSE
fuc-0.38.0.dist-info/METADATA
fuc-0.38.0.dist-info/WHEEL
fuc-0.38.0.dist-info/entry_points.txt
fuc-0.38.0.dist-info/top_level.txt
fuc-0.38.0.dist-info/RECORD
