Metadata-Version: 2.1
Name: fuc
Version: 0.38.0
Summary: Frequently used commands in bioinformatics
Home-page: https://github.com/sbslee/fuc
Author: Seung-been "Steven" Lee
Author-email: sbstevenlee@gmail.com
License: MIT
Classifier: Programming Language :: Python :: 3
Classifier: License :: OSI Approved :: MIT License
License-File: LICENSE
Requires-Dist: biopython
Requires-Dist: lxml
Requires-Dist: matplotlib
Requires-Dist: matplotlib-venn
Requires-Dist: numpy
Requires-Dist: pandas
Requires-Dist: pyranges
Requires-Dist: pysam
Requires-Dist: scipy
Requires-Dist: seaborn
Requires-Dist: statsmodels
